odoo9_addon_contract_mandate-9.0.1.0.0-py2.7-nspkg.pth
odoo9_addon_contract_mandate-9.0.1.0.0.dist-info/DESCRIPTION.rst
odoo9_addon_contract_mandate-9.0.1.0.0.dist-info/METADATA
odoo9_addon_contract_mandate-9.0.1.0.0.dist-info/RECORD
odoo9_addon_contract_mandate-9.0.1.0.0.dist-info/WHEEL
odoo9_addon_contract_mandate-9.0.1.0.0.dist-info/metadata.json
odoo9_addon_contract_mandate-9.0.1.0.0.dist-info/namespace_packages.txt
odoo9_addon_contract_mandate-9.0.1.0.0.dist-info/top_level.txt
odoo_addons/contract_mandate/README.rst
odoo_addons/contract_mandate/__init__.py
odoo_addons/contract_mandate/__openerp__.py
odoo_addons/contract_mandate/i18n/es.po
odoo_addons/contract_mandate/models/__init__.py
odoo_addons/contract_mandate/models/contract.py
odoo_addons/contract_mandate/tests/__init__.py
odoo_addons/contract_mandate/tests/test_contract_mandate.py
odoo_addons/contract_mandate/views/contract_view.xml
