Metadata-Version: 2.0
Name: odoo9-addon-contract-mandate
Version: 9.0.1.0.0
Summary: Mandate in contracts and their invoices
Home-page: http://www.tecnativa.com
Author: Tecnativa, Odoo Community Association (OCA)
Author-email: support@odoo-community.org
License: AGPL-3
Platform: UNKNOWN
Classifier: Programming Language :: Python :: 2.7
Classifier: Framework :: Odoo
Classifier: License :: OSI Approved :: GNU Affero General Public License v3
Requires-Dist: odoo (<9.1a,>=9.0a)
Requires-Dist: odoo9-addon-account-banking-mandate
Requires-Dist: odoo9-addon-contract-payment-mode
